espeakui/__init__.py
espeakui/espeak_urwid.py
espeakui/espeaker.py
espeakui/espeakui.py
espeakui/translate.py
espeakui-0.1.dist-info/METADATA
espeakui-0.1.dist-info/WHEEL
espeakui-0.1.dist-info/top_level.txt
espeakui-0.1.dist-info/RECORD
