Metadata-Version: 2.1
Name: espeakui
Version: 0.1
Summary: A text-to-speech interface with mplayer-like bindings, using espeak
Home-page: https://github.com/asrp/espeakui
Author: asrp
Author-email: asrp@email.com
License: UNKNOWN
Keywords: espeak ui tts
Platform: UNKNOWN
Requires-Dist: python-espeak
Requires-Dist: guess-language
Provides-Extra: full
Requires-Dist: urwid ; extra == 'full'
